tdi_sdk/__init__.py
tdi_sdk/main.py
tdi_sdk-0.0.2.dist-info/LICENSE
tdi_sdk-0.0.2.dist-info/METADATA
tdi_sdk-0.0.2.dist-info/WHEEL
tdi_sdk-0.0.2.dist-info/top_level.txt
tdi_sdk-0.0.2.dist-info/RECORD
