Metadata-Version: 2.1
Name: tdi-sdk
Version: 0.0.2
Summary: Simple SDK to use TDI services
Home-page: https://github.com/denisgermano/tdi_sdk
Author: Denis Germano
Author-email: dlcgermano@gmai.com
License: UNKNOWN
Project-URL: Bug Tracker, https://github.com/denisgermano/tdi_sdk/issues
Platform: UNKNOWN
Classifier: Programming Language :: Python :: 3
Classifier: License :: OSI Approved :: MIT License
Classifier: Operating System :: OS Independent
Requires-Python: >=3.7
License-File: LICENSE
